oracle_utils/__init__.py
oracle_utils/admin.py
oracle_utils/apps.py
oracle_utils/models.py
oracle_utils/tests.py
oracle_utils/views.py
oracle_utils/migrations/__init__.py
django_oracle_utils-0.0.1.dist-info/LICENSE
django_oracle_utils-0.0.1.dist-info/METADATA
django_oracle_utils-0.0.1.dist-info/WHEEL
django_oracle_utils-0.0.1.dist-info/top_level.txt
django_oracle_utils-0.0.1.dist-info/RECORD
