Metadata-Version: 2.1
Name: django-oracle-utils
Version: 0.0.1
Summary: Adds support for additional Oracle functions
Home-page: https://github.com/rmeyers4/django-oracle-utils
Author: Robbie Meyers
Author-email: robbie.meyers@gmail.com
License: UNKNOWN
Platform: UNKNOWN
Classifier: Programming Language :: Python :: 3
Classifier: License :: OSI Approved :: MIT License
Classifier: Operating System :: OS Independent
Requires-Python: >=3.6
